{"errors":[],"warnings":[],"namedChunkGroups":{"polyfill":{"chunks":[1,5],"assets":["webpack-runtime-ea9798c40ec5d928f7db.js","webpack-runtime-ea9798c40ec5d928f7db.js.map","polyfill-037656030c336817faa1.js","polyfill-037656030c336817faa1.js.map"],"children":{},"childAssets":{}},"app":{"chunks":[1,0,4,2],"assets":["webpack-runtime-ea9798c40ec5d928f7db.js","webpack-runtime-ea9798c40ec5d928f7db.js.map","styles.d7585e0d9c609bbe3ca7.css","styles-407fe62976dc5310c43e.js","styles-407fe62976dc5310c43e.js.map","framework-17f9eab80f4183b03f0e.js","framework-17f9eab80f4183b03f0e.js.map","app-7437bd0e8a7583880757.js","app-7437bd0e8a7583880757.js.map"],"children":{},"childAssets":{}},"component---src-pages-index-js":{"chunks":[0,3],"assets":["styles.d7585e0d9c609bbe3ca7.css","styles-407fe62976dc5310c43e.js","styles-407fe62976dc5310c43e.js.map","component---src-pages-index-js-5b52276ea58ec51bd11e.js","component---src-pages-index-js-5b52276ea58ec51bd11e.js.map"],"children":{},"childAssets":{}}},"assetsByChunkName":{"polyfill":["webpack-runtime-ea9798c40ec5d928f7db.js","polyfill-037656030c336817faa1.js"],"app":["webpack-runtime-ea9798c40ec5d928f7db.js","styles.d7585e0d9c609bbe3ca7.css","styles-407fe62976dc5310c43e.js","framework-17f9eab80f4183b03f0e.js","app-7437bd0e8a7583880757.js"],"component---src-pages-index-js":["styles.d7585e0d9c609bbe3ca7.css","styles-407fe62976dc5310c43e.js","component---src-pages-index-js-5b52276ea58ec51bd11e.js"]}}